mypackage/__init__.py
mypackage/decorators.py
mypackage/descriptors.py
mypackage/generators.py
mypackage/iterators.py
mypackage-tanyapeshkova/__init__.py
mypackage-tanyapeshkova/decorators.py
mypackage-tanyapeshkova/descriptors.py
mypackage-tanyapeshkova/generators.py
mypackage-tanyapeshkova/iterators.py
mypackage_tanyapeshkova/__init__.py
mypackage_tanyapeshkova/decorators.py
mypackage_tanyapeshkova/descriptors.py
mypackage_tanyapeshkova/generators.py
mypackage_tanyapeshkova/iterators.py
tests/__init__.py
tests/test_decorators.py
tests/test_descriptors.py
tests/test_generators.py
tests/test_iterators.py
mypackage_tanyapeshkova-0.3.dist-info/METADATA
mypackage_tanyapeshkova-0.3.dist-info/WHEEL
mypackage_tanyapeshkova-0.3.dist-info/top_level.txt
mypackage_tanyapeshkova-0.3.dist-info/RECORD
